{"type": "Feature", "id": 12512819, "properties": {"woe:id": 12512819, "woe:parent_id": 28743689, "woe:name": "Anaa Airport", "woe:placetype": 14, "woe:placetype_name": "Airport", "woe:lang": "ENG", "iso:country": "PF", "meta:provider": ["geoplanet:7.3.1", "geoplanet:7.3.2", "geoplanet:7.4.0", "geoplanet:7.4.1", "geoplanet:7.5.1", "geoplanet:7.5.2", "geoplanet:7.6.0", "geoplanet:7.8.1", "geoplanet:7.9.0", "geoplanet:7.10.0", "geoplanet:8.0.0", "woeplanet:8.0.0"], "meta:indexed": "2020-08-20T21:02:04.749753", "meta:updated": "2020-08-22T03:00:17.728992", "woe:hierarchy": {"continent": 24865674, "country": 23424817, "town": 0, "planet": 1, "county": 28743689, "suburb": 0, "state": 24549702, "region": 0, "localadmin": 0}, "woe:timezone_id": 28350946, "woe:hash": "2ubt1py1wf2n", "woe:centroid": [-145.4944, -17.359501], "geom:latitude": -17.359501, "geom:longitude": -145.4944, "geom:hash": "2ubt1py1wf2n", "woe:latitude": -17.359501, "geom:centroid": [-145.4944, -17.359501], "woe:longitude": -145.4944, "woe:repo": "woeplanet-airport-pf"}, "geometry": {"coordinates": [-145.4944, -17.359501], "type": "Point"}}