{"type": "Feature", "id": 12512835, "geometry": {"type": "Point", "coordinates": [-148.232498, -15.1197]}, "properties": {"woe:id": 12512835, "woe:parent_id": 28743701, "woe:name": "Tikehau Airport", "woe:placetype": 14, "woe:placetype_name": "Airport", "woe:lang": "ENG", "iso:country": "PF", "meta:provider": ["geoplanet:7.3.1", "geoplanet:7.3.2", "geoplanet:7.4.0", "geoplanet:7.4.1", "geoplanet:7.5.1", "geoplanet:7.5.2", "geoplanet:7.6.0", "geoplanet:7.8.1", "geoplanet:7.9.0", "geoplanet:7.10.0", "geoplanet:8.0.0", "woeplanet:8.0.0"], "meta:indexed": "2020-08-20T21:02:04.761527", "meta:updated": "2020-10-14T11:19:25.321690", "woe:hierarchy": {"continent": 24865674, "country": 23424817, "town": 0, "planet": 1, "county": 28743701, "suburb": 0, "state": 24549702, "region": 0, "localadmin": 0}, "woe:timezone_id": 28350946, "woe:hash": "2tq9fzs3k7wk", "woe:centroid": [-148.232498, -15.1197], "geom:latitude": -15.1197, "geom:longitude": -148.232498, "geom:hash": "2tq9fzs3k7wk", "woe:latitude": -15.1197, "geom:centroid": [-148.232498, -15.1197], "woe:longitude": -148.232498, "woe:repo": "woeplanet-airport-pf", "geom:area": 0.0, "woe:scale": 19}}